getwowdataasync/__init__.py
getwowdataasync/exceptions.py
getwowdataasync/getdata.py
getwowdataasync/helpers.py
getwowdataasync/urls.py
get_wow_data_async-0.2.2.1.dist-info/METADATA
get_wow_data_async-0.2.2.1.dist-info/WHEEL
get_wow_data_async-0.2.2.1.dist-info/top_level.txt
get_wow_data_async-0.2.2.1.dist-info/RECORD
