Metadata-Version: 2.1
Name: get-wow-data-async
Version: 0.2.2.1
Summary: Provides async methods to make requests to specific World of Warcraft API's
Home-page: https://github.com/JackBorah/get-wow-data-async
Author: Jack Borah
Author-email: borahjack@gmail.com
License: MIT
Keywords: World of Warcraft
Platform: any
Classifier: Intended Audience :: Developers
Classifier: Programming Language :: Python :: 3
Classifier: Operating System :: OS Independent
Classifier: License :: OSI Approved :: MIT License
Classifier: Topic :: Software Development :: Libraries :: Python Modules
Requires-Dist: httpx
Requires-Dist: python-dotenv
